astropack/__init__.py
astropack/evaluation/__init__.py
astropack/evaluation/_graphics.py
astropack/evaluation/_metrics.py
astropack/models/__init__.py
astropack/models/_models.py
astropack/models/_predictors.py
astropack/preprocess/__init__.py
astropack/preprocess/_functions.py
astropack/tuning/__init__.py
astropack/tuning/_tuner.py
astropack-2.0.1.dist-info/LICENSE
astropack-2.0.1.dist-info/METADATA
astropack-2.0.1.dist-info/WHEEL
astropack-2.0.1.dist-info/top_level.txt
astropack-2.0.1.dist-info/RECORD
