Metadata-Version: 2.1
Name: astropack
Version: 2.0.1
Summary: Data Processing and Machine Learning Functions for Astronomy Applications
Author: Vinicius Cordeiro
Author-email: cdro.vinicius@gmail.com
License: MIT License
Keywords: astronomy,machinelearning,ml
Classifier: License :: OSI Approved :: MIT License
Classifier: Programming Language :: Python :: 3 :: Only
Requires-Python: >=3.7
License-File: LICENSE
Requires-Dist: scikit-learn
Requires-Dist: pandas
Requires-Dist: numpy
Requires-Dist: pre-commit
